{"Paneer": "none", "Passendale Cheese": "none", "Passendale": "none", "Pa\u0161ki Sir": "none", "Prgica": "none", "Pdo": "none", "P\u00e1lpusztai": "none", "Pann\u00f3nia": "none", "Pljevaljski Sir": "none", "Podgori\u010dki Sir": "none", "Pultost": "none", "Pule Cheese": "none", "Parenica": "none", "Pr\u00e4stost": "none", "Pepper Jack Cheese": "none", "Pinconning Cheese": "none", "Provel Cheese": "none", "Panquehue": "none", "Port Wine Cheese": "none", "Palmyra_Palm": "none", "Papaya": "none", "Passion_Fruit": "none", "Pawpaw": "none", "Peach": "none", "Peach_Palm": "none", "Peanut": "none", "Peanut_Butter_Fruit": "none", "Pear": "none", "Pecan": "none", "Pentadin''": "none", "Pepino": "none", "Pequi": "none", "Persian_Lime": "none", "Peumo": "none", "Phalsa": "none", "Pigeon_Pea": "none", "Pigeon_Plum": "none", "Pigface": "none", "Pili_Nut": "none", "Pindo_Palm": "none", "Pineapple": "none", "Pineapple_Guava": "none", "Pink_Flowered_Native_Raspberry": "none", "Pistachio": "none", "Pitomba": "none", "Plum": "none", "Pluot": "none", "Pois_Doux": "none", "Pomegranate": "none", "Pomelo": "none", "Pommecythere": "none", "Pommerac": "none", "Pond_Apple": "none", "Prickly_Pear": "none", "Pulasan": "none", "Pummelo": "none", "Pumpkin": "none", "Pupunha": "none", "Purple_Apple_Berry": "none", "Purple_Granadilla": "none", "Purple_Guava": "none", "Purple_Mombin": "none", "Portulaca Oleracea": "none", "Pteridium Aquilinumathyrium Esculentum": "none", "Plantago Major": "none", "Pak Choy (\u767d\u83dc Bok Choy)": "none", "Paracress": "none", "Pea (Sprouts\u00a0/ Leaves)": "none", "Pisum Sativum": "none", "Poke": "none", "Phytolacca Americana": "none", "Persea Americana": "none", "Praecitrullus Fistulosus": "none", "Physalis Philadelphica": "none", "Phaseolus Vulgaris": "none", "Phaseolus Lunatus": "none", "Pea": "none", "Pigeon Pea": "none", "Phaseolus Coccineus": "none", "Pisum Sativum (Macrocarpon)": "none", "Pisum Sativum (Saccharatum)": "none", "Phaseolus Acutifolius": "none", "Psophocarpus Tetragonolobus": "none", "Pearl Onion": "none", "Potato Onion": "none", "Prussian Asparagus": "none", "Pachyrhizus Ahipa": "none", "Petroselinum Crispum Tuberosum": "none", "Pachyrhizus Erosus": "none", "Parsnip": "none", "Pastinaca Sativa": "none", "Pignut": "none", "Potato": "none", "Prairie Turnip": "none", "Psoralea Esculenta": "none", "Palmaria Palmata": "none", "Porphyra": "none", "Paprika": "none", "Parsley": "none", "Peppermint": "none", "Perilla": "none", "Peruvian pepper": "none", "Puerto Rican cuisine": "none", "Porophyllum ruderale": "none", "Persicaria odorata": "none", "Piper auritum": "none", "Perilla frutescens": "none", "Piper cubeba": "none", "Poppy seed": "none", "Piper borbonense": "none", "Piri piri": "none", "Panch phoron": "none", "Persillade": "none", "Powder-douce": "none", "Pumpkin pie spice": "none", "Pain d'Epi ": "none", "Pain de mie": "none", "Pan dulce ": "none", "Panbrioche": "none", "Pancake": "none", "Pandesal": "none", "Pandoro": "none", "Pane carasau": "none", "Pane di Altamura": "none", "Pane ticinese": "none", "Panettone": "none", "Panfocaccia": "none", "Papadum": "none", "Paratha": "none", "Parotta": "none", "Paximathia": "none", "Peg bread": "none", "Penia ": "none", "Piadina": "none", "Pistolet ": "none", "Pita": "none", "Pizza": "none", "Poga\u010da": "none", "Portuguese sweet bread": "none", "Potato bread": "none", "Potato pancake": "none", "Potbrood": "none", "Pretzel": "none", "Proja": "none", "Pumpernickel": "none", "Puran Poli": "none", "Portabello": "none", "Pagoda Tree": "none", "Palo Verde": "none", "Peppercorns": "none", "Pork": "none", "Pot": "none", "Pin-Bone": "none", "Picnic": "none", "Pufferfish": "none", "Parrotfish": "none", "Patagonian": "none", "Pike": "none", "Pilchard": "none", "Pollock": "none", "Pomfret": "none", "Pompano": "none", "Periwinkle": "none", "Peanuts": "none", "Pecans": "none", "Pili": "none", "Pine": "none", "Pistachios": "none", "Pickles": "None"}